{
    "deck1-essentials": [
        { "front": "Hola", "back": "Hello" },
        { "front": "Adiós", "back": "Goodbye" },
        { "front": "Por favor", "back": "Please" },
        { "front": "Gracias", "back": "Thank you" },
        { "front": "De nada", "back": "You're welcome" },
        { "front": "Lo siento", "back": "I'm sorry" },
        { "front": "Disculpe", "back": "Excuse me" },
        { "front": "¿Cómo estás?", "back": "How are you? (informal)" },
        { "front": "¿Cómo está usted?", "back": "How are you? (formal)" },
        { "front": "Bien, gracias", "back": "Good, thank you" },
        { "front": "¿Cuál es tu nombre?", "back": "What's your name? (informal)" },
        { "front": "Me llamo…", "back": "My name is…" },
        { "front": "Mucho gusto", "back": "Nice to meet you" },
        { "front": "¿Habla inglés?", "back": "Do you speak English?" },
        { "front": "No hablo español", "back": "I don't speak Spanish" },
        { "front": "Un poco", "back": "A little" },
        { "front": "No entiendo", "back": "I don't understand" },
        { "front": "¿Puede ayudarme?", "back": "Can you help me?" },
        { "front": "¿Dónde está el baño?", "back": "Where is the bathroom?" },
        { "front": "¿Cuánto cuesta?", "back": "How much does it cost?" },
        { "front": "Sí", "back": "Yes" },
        { "front": "No", "back": "No" },
        { "front": "Tal vez", "back": "Maybe" },
        { "front": "Está bien", "back": "It's okay / It's fine" },
        { "front": "No hay problema", "back": "No problem" }
    ],
    "deck2-questions-and-responses": [
        { "front": "¿Quién?", "back": "Who?" },
        { "front": "¿Qué?", "back": "What?" },
        { "front": "¿Dónde?", "back": "Where?" },
        { "front": "¿Cuándo?", "back": "When?" },
        { "front": "¿Por qué?", "back": "Why?" },
        { "front": "¿Cómo?", "back": "How?" },
        { "front": "¿Tienes...?", "back": "Do you have...?" },
        { "front": "¿Puedo...?", "back": "Can I...?" },
        { "front": "¿Cuánto cuesta?", "back": "How much does it cost?" },
        { "front": "¿Qué hora es?", "back": "What time is it?" },
        { "front": "¿Dónde está el baño?", "back": "Where is the bathroom?" },
        { "front": "No lo sé", "back": "I don't know" },
        { "front": "Tal vez", "back": "Maybe" },
        { "front": "Creo que sí", "back": "I think so" },
        { "front": "Sí", "back": "Yes" },
        { "front": "No", "back": "No" },
        { "front": "¿Podrías ayudarme?", "back": "Could you help me?" },
        { "front": "¿Qué significa esto?", "back": "What does this mean?" },
        { "front": "¿Está bien si...?", "back": "Is it okay if...?" },
        { "front": "¿Qué haces?", "back": "What are you doing?" },
        { "front": "¿Qué pasa?", "back": "What's happening?" },
        { "front": "¿Dónde vives?", "back": "Where do you live?" },
        { "front": "¿Qué te gusta hacer?", "back": "What do you like to do?" },
        { "front": "¿Cómo estás?", "back": "How are you?" },
        { "front": "¿Y tú?", "back": "And you?" }
    ],
    "deck3-daily-life-and-household-vocab": [
        { "front": "La sala", "back": "The living room" },
        { "front": "La cocina", "back": "The kitchen" },
        { "front": "El dormitorio", "back": "The bedroom" },
        { "front": "El baño", "back": "The bathroom" },
        { "front": "El comedor", "back": "The dining room" },
        { "front": "El pasillo", "back": "The hallway" },
        { "front": "El sofá", "back": "The sofa" },
        { "front": "La cama", "back": "The bed" },
        { "front": "La mesa", "back": "The table" },
        { "front": "La silla", "back": "The chair" },
        { "front": "La lámpara", "back": "The lamp" },
        { "front": "La nevera", "back": "The refrigerator" },
        { "front": "La estufa", "back": "The stove" },
        { "front": "La lavadora", "back": "The washing machine" },
        { "front": "El microondas", "back": "The microwave" },
        { "front": "Limpiar", "back": "To clean" },
        { "front": "Cocinar", "back": "To cook" },
        { "front": "Descansar", "back": "To rest" },
        { "front": "Lavar los platos", "back": "To wash the dishes" },
        { "front": "Hacer la cama", "back": "To make the bed" },
        { "front": "Pasar la aspiradora", "back": "To vacuum" },
        { "front": "Sacar la basura", "back": "To take out the trash" },
        { "front": "El padre", "back": "The father" },
        { "front": "La madre", "back": "The mother" },
        { "front": "El hermano", "back": "The brother" },
        { "front": "La hermana", "back": "The sister" },
        { "front": "El hijo", "back": "The son" },
        { "front": "La hija", "back": "The daughter" },
        { "front": "El abuelo", "back": "The grandfather" },
        { "front": "La abuela", "back": "The grandmother" }
    ],
    "deck4-food-drinks-and-ordering": [
        { "front": "El desayuno", "back": "Breakfast" },
        { "front": "El almuerzo", "back": "Lunch" },
        { "front": "La cena", "back": "Dinner" },
        { "front": "La merienda", "back": "Snack" },
        { "front": "El pan", "back": "Bread" },
        { "front": "El arroz", "back": "Rice" },
        { "front": "La carne", "back": "Meat" },
        { "front": "El pollo", "back": "Chicken" },
        { "front": "El pescado", "back": "Fish" },
        { "front": "La ensalada", "back": "Salad" },
        { "front": "La fruta", "back": "Fruit" },
        { "front": "Las verduras", "back": "Vegetables" },
        { "front": "El postre", "back": "Dessert" },
        { "front": "El agua", "back": "Water" },
        { "front": "El jugo", "back": "Juice" },
        { "front": "El café", "back": "Coffee" },
        { "front": "La cerveza", "back": "Beer" },
        { "front": "La cuenta, por favor.", "back": "The bill, please." },
        { "front": "¿Qué recomienda?", "back": "What do you recommend?" },
        { "front": "Quisiera...", "back": "I would like..." },
        { "front": "¿Tiene opciones vegetarianas?", "back": "Do you have vegetarian options?" },
        { "front": "Estoy lleno(a)", "back": "I'm full" },
        { "front": "Me gusta", "back": "I like" },
        { "front": "No me gusta", "back": "I don't like" },
        { "front": "No quiero", "back": "I don't want" },
        { "front": "¿Puedo ver el menú?", "back": "Can I see the menu?" },
        { "front": "Está delicioso", "back": "It is delicious" },
        { "front": "Para llevar", "back": "To go / Takeout" },
        { "front": "Para aquí", "back": "For here" },
        { "front": "Tengo alergia a...", "back": "I'm allergic to..." }
    ],
    "deck5-directions-and-getting-around": [
        { "front": "a la izquierda", "back": "to the left" },
        { "front": "a la derecha", "back": "to the right" },
        { "front": "recto / derecho", "back": "straight ahead" },
        { "front": "cerca", "back": "near" },
        { "front": "lejos", "back": "far" },
        { "front": "el norte", "back": "north" },
        { "front": "el sur", "back": "south" },
        { "front": "el este", "back": "east" },
        { "front": "el oeste", "back": "west" },
        { "front": "el cruce", "back": "intersection" },
        { "front": "la esquina", "back": "corner" },
        { "front": "la parada", "back": "stop (bus/train)" },
        { "front": "el semáforo", "back": "traffic light" },
        { "front": "el puente", "back": "bridge" },
        { "front": "el túnel", "back": "tunnel" },

        { "front": "el autobús", "back": "bus" },
        { "front": "el tren", "back": "train" },
        { "front": "el metro", "back": "subway" },
        { "front": "el taxi", "back": "taxi" },
        { "front": "el coche / el carro", "back": "car" },
        { "front": "la bicicleta", "back": "bicycle" },
        { "front": "a pie", "back": "on foot" },

        { "front": "¿Dónde está...?", "back": "Where is...?" },
        { "front": "¿Cómo llego a...?", "back": "How do I get to...?" },
        { "front": "¿Está lejos?", "back": "Is it far?" },
        { "front": "¿Puede ayudarme?", "back": "Can you help me?" },
        { "front": "Estoy perdido(a)", "back": "I'm lost" },

        { "front": "el hospital", "back": "hospital" },
        { "front": "el banco", "back": "bank" },
        { "front": "la estación", "back": "station" },
        { "front": "el aeropuerto", "back": "airport" },
        { "front": "el hotel", "back": "hotel" },
        { "front": "el restaurante", "back": "restaurant" },
        { "front": "el centro", "back": "downtown / city center" }
    ],
    "deck6-describing-people-and-emotions": [
        { "front": "alto / alta", "back": "tall" },
        { "front": "bajo / baja", "back": "short" },
        { "front": "delgado / delgada", "back": "thin / slim" },
        { "front": "gordo / gorda", "back": "fat / overweight" },
        { "front": "guapo / guapa", "back": "handsome / beautiful" },
        { "front": "feo / fea", "back": "ugly" },
        { "front": "joven", "back": "young" },
        { "front": "viejo / vieja", "back": "old" },
        { "front": "fuerte", "back": "strong" },
        { "front": "débil", "back": "weak" },
        { "front": "moreno / morena", "back": "dark-haired / brunette" },
        { "front": "rubio / rubia", "back": "blonde" },

        { "front": "simpático / simpática", "back": "nice / friendly" },
        { "front": "antipático / antipática", "back": "mean / unfriendly" },
        { "front": "gracioso / graciosa", "back": "funny" },
        { "front": "serio / seria", "back": "serious" },
        { "front": "tímido / tímida", "back": "shy" },
        { "front": "extrovertido / extrovertida", "back": "outgoing" },
        { "front": "inteligente", "back": "smart / intelligent" },
        { "front": "trabajador / trabajadora", "back": "hardworking" },
        { "front": "perezoso / perezosa", "back": "lazy" },

        { "front": "feliz", "back": "happy" },
        { "front": "triste", "back": "sad" },
        { "front": "enojado / enojada", "back": "angry" },
        { "front": "cansado / cansada", "back": "tired" },
        { "front": "emocionado / emocionada", "back": "excited" },
        { "front": "nervioso / nerviosa", "back": "nervous" },
        { "front": "relajado / relajada", "back": "relaxed" },
        { "front": "asustado / asustada", "back": "scared" },
        { "front": "aburrido / aburrida", "back": "bored" },

        { "front": "mi amigo / mi amiga", "back": "my friend" },
        { "front": "mi hermano / mi hermana", "back": "my brother / my sister" },
        { "front": "mi madre / mi padre", "back": "my mom / my dad" },
        { "front": "mi pareja", "back": "my partner" },
        { "front": "mi novio / mi novia", "back": "my boyfriend / my girlfriend" },
        { "front": "conozco a alguien", "back": "I know someone" },
        { "front": "me llevo bien con...", "back": "I get along with..." },
        { "front": "estoy enamorado / enamorada", "back": "I'm in love" }
    ],
    "deck7-time-days-and-routines": [
        { "front": "lunes", "back": "Monday" },
        { "front": "martes", "back": "Tuesday" },
        { "front": "miércoles", "back": "Wednesday" },
        { "front": "jueves", "back": "Thursday" },
        { "front": "viernes", "back": "Friday" },
        { "front": "sábado", "back": "Saturday" },
        { "front": "domingo", "back": "Sunday" },

        { "front": "enero", "back": "January" },
        { "front": "febrero", "back": "February" },
        { "front": "marzo", "back": "March" },
        { "front": "abril", "back": "April" },
        { "front": "mayo", "back": "May" },
        { "front": "junio", "back": "June" },
        { "front": "julio", "back": "July" },
        { "front": "agosto", "back": "August" },
        { "front": "septiembre", "back": "September" },
        { "front": "octubre", "back": "October" },
        { "front": "noviembre", "back": "November" },
        { "front": "diciembre", "back": "December" },

        { "front": "la primavera", "back": "spring" },
        { "front": "el verano", "back": "summer" },
        { "front": "el otoño", "back": "autumn / fall" },
        { "front": "el invierno", "back": "winter" },

        { "front": "¿Qué hora es?", "back": "What time is it?" },
        { "front": "Es la una", "back": "It's one o'clock" },
        { "front": "Son las dos (tres, cuatro...)", "back": "It's two (three, four...) o'clock" },
        { "front": "y cuarto", "back": "quarter past" },
        { "front": "y media", "back": "half past" },
        { "front": "menos cuarto", "back": "quarter to" },
        { "front": "de la mañana", "back": "in the morning" },
        { "front": "de la tarde", "back": "in the afternoon" },
        { "front": "de la noche", "back": "at night" },

        { "front": "me levanto", "back": "I get up" },
        { "front": "me ducho", "back": "I shower" },
        { "front": "desayuno", "back": "I eat breakfast" },
        { "front": "voy al trabajo", "back": "I go to work" },
        { "front": "almuerzo", "back": "I eat lunch" },
        { "front": "vuelvo a casa", "back": "I return home" },
        { "front": "ceno", "back": "I eat dinner" },
        { "front": "me acuesto", "back": "I go to bed" },

        { "front": "siempre", "back": "always" },
        { "front": "a veces", "back": "sometimes" },
        { "front": "nunca", "back": "never" },
        { "front": "todos los días", "back": "every day" },
        { "front": "una vez a la semana", "back": "once a week" },
        { "front": "cada mañana", "back": "every morning" }
    ],
    "deck8-commons-verbs-in-context": [
        { "front": "ser", "back": "to be (essential quality)" },
        { "front": "estar", "back": "to be (state or location)" },
        { "front": "tener", "back": "to have" },
        { "front": "ir", "back": "to go" },
        { "front": "hacer", "back": "to do / to make" },

        { "front": "Soy estudiante", "back": "I am a student" },
        { "front": "Estoy cansado", "back": "I am tired" },
        { "front": "Tengo una pregunta", "back": "I have a question" },
        { "front": "Voy al trabajo", "back": "I go to work" },
        { "front": "Hago la tarea", "back": "I do the homework" },

        { "front": "tomar una ducha", "back": "to take a shower" },
        { "front": "hacer comida", "back": "to make food" },
        { "front": "leer un libro", "back": "to read a book" },
        { "front": "ver la televisión", "back": "to watch TV" },
        { "front": "escuchar música", "back": "to listen to music" },

        { "front": "me levanto", "back": "I get up" },
        { "front": "me ducho", "back": "I shower" },
        { "front": "me visto", "back": "I get dressed" },
        { "front": "me cepillo los dientes", "back": "I brush my teeth" },
        { "front": "me acuesto", "back": "I go to bed" },

        { "front": "Él es simpático", "back": "He is nice" },
        { "front": "Ella está feliz", "back": "She is happy" },
        { "front": "Tenemos hambre", "back": "We are hungry" },
        { "front": "Van al parque", "back": "They go to the park" },
        { "front": "¿Qué haces?", "back": "What are you doing?" },

        { "front": "levantarse", "back": "to get up" },
        { "front": "ducharse", "back": "to shower" },
        { "front": "vestirse", "back": "to get dressed" },
        { "front": "cepillarse los dientes", "back": "to brush one's teeth" },
        { "front": "acostarse", "back": "to go to bed" }
    ],
    "deck9-real-conversations": [
        { "front": "¿A qué te dedicas?", "back": "What do you do?" },
        { "front": "¿De dónde eres?", "back": "Where are you from?" },
        { "front": "¿Cuál es tu comida favorita?", "back": "What's your favorite food?" },
        { "front": "¿Qué te gusta hacer en tu tiempo libre?", "back": "What do you like to do in your free time?" },
        { "front": "¿Tienes hermanos?", "back": "Do you have siblings?" },

        { "front": "Hace buen tiempo hoy", "back": "The weather is nice today" },
        { "front": "¡Qué interesante!", "back": "How interesting!" },
        { "front": "¿De verdad?", "back": "Really?" },
        { "front": "¿Qué opinas?", "back": "What do you think?" },
        { "front": "Creo que sí", "back": "I think so" },

        { "front": "Estoy aprendiendo español", "back": "I am learning Spanish" },
        { "front": "¿Has estado en México?", "back": "Have you been to Mexico?" },
        { "front": "Fui al cine ayer", "back": "I went to the movies yesterday" },
        { "front": "Voy a estudiar esta noche", "back": "I'm going to study tonight" },
        { "front": "¿Qué hiciste el fin de semana?", "back": "What did you do on the weekend?" },

        { "front": "¿Cómo estuvo tu día?", "back": "How was your day?" },
        { "front": "Estuvo bien, gracias", "back": "It was good, thank you" },
        { "front": "¿Qué planes tienes para mañana?", "back": "What are your plans for tomorrow?" },
        { "front": "Me gusta viajar", "back": "I like to travel" },
        { "front": "No me gusta esperar", "back": "I don't like to wait" },

        { "front": "¿Cuál es tu película favorita?", "back": "What is your favorite movie?" },
        { "front": "Me encanta la música", "back": "I love music" },
        { "front": "¿Te gusta cocinar?", "back": "Do you like to cook?" },
        { "front": "Sí, cocino todos los días", "back": "Yes, I cook every day" },
        { "front": "No mucho, prefiero pedir comida", "back": "Not really, I prefer ordering food" }
    ],
    "deck10-travel-and-cultural-expressions": [
        { "front": "Pasaporte", "back": "Passport" },
        { "front": "Boleto / Billete", "back": "Ticket (Latin America / Spain)" },
        { "front": "Hotel", "back": "Hotel" },
        { "front": "Reservación / Reserva", "back": "Reservation" },
        { "front": "Equipaje", "back": "Luggage" },

        { "front": "¿Dónde está la estación de tren?", "back": "Where is the train station?" },
        { "front": "Necesito un taxi", "back": "I need a taxi" },
        { "front": "¿Cuánto cuesta por noche?", "back": "How much does it cost per night?" },
        { "front": "¿Tienen Wi-Fi?", "back": "Do you have Wi-Fi?" },
        { "front": "La cuenta, por favor", "back": "The check, please" },

        { "front": "¡Órale!", "back": "Wow! / Let's go! (Mexico)" },
        { "front": "Vale", "back": "Okay (Spain)" },
        { "front": "Che", "back": "Dude / Hey (Argentina)" },
        { "front": "¡Qué padre!", "back": "How cool! (Mexico)" },
        { "front": "Pilas", "back": "Be alert / heads up (Guatemala, Colombia)" },

        { "front": "No des propina en Japón", "back": "Don't tip in Japan (cultural tip)" },
        { "front": "En España, la comida es tarde", "back": "In Spain, meals are eaten late" },
        { "front": "En México, la cortesía es importante", "back": "In Mexico, politeness is important" },
        { "front": "Saludar con beso en la mejilla", "back": "Greet with a kiss on the cheek (common in Latin America/Spain)" },
        { "front": "No hables de política con extraños", "back": "Don't talk politics with strangers" },

        { "front": "Estoy perdido/a", "back": "I'm lost" },
        { "front": "Necesito ayuda", "back": "I need help" },
        { "front": "¿Dónde está la embajada?", "back": "Where is the embassy?" },
        { "front": "Mi vuelo fue cancelado", "back": "My flight was canceled" },
        { "front": "¿Dónde puedo cambiar dinero?", "back": "Where can I exchange money?" }
    ]
}